min_soup/__init__.py
min_soup/minimal_soup.py
min_soup/soup_element.py
min_soup-1.0.dist-info/METADATA
min_soup-1.0.dist-info/WHEEL
min_soup-1.0.dist-info/top_level.txt
min_soup-1.0.dist-info/RECORD
