Metadata-Version: 2.1
Name: min-soup
Version: 1.0
Summary: Бібліотека для роботи з HTML-документами
Home-page: https://github.com/nikitin-eti/min_soup
Author: Dmytro Mitkin
Author-email: Dmytro Mitkin <159967771+nikitin-eti@users.noreply.github.com>
Project-URL: Homepage, https://github.com/nikitin-eti/min_soup
Classifier: Programming Language :: Python :: 3
Classifier: License :: OSI Approved :: MIT License
Classifier: Operating System :: OS Independent
Requires-Python: >=3.6
